Metadata-Version: 1.0
Name: testpip
Version: 0.1
Summary: The funniest joke in the world
Home-page: http://github.com/n89nanda/testpip
Author: Flying Circus
Author-email: n89nanda@gmail.com@gmail.com
License: MIT
Platform: UNKNOWN
